{"is_source_file": true, "format": "JavaScript", "description": "Main application component of the React frontend for a simple notes web application, managing themes and rendering a layout with a Navbar and placeholder content for notes.", "external_files": ["./App.css", "./components/Navbar", "./components/Navbar.css", "./ThemeContext"], "external_methods": ["useTheme"], "published": ["App"], "classes": [], "methods": [{"name": "App()", "scope": "", "scopeKind": "", "description": "unavailable"}], "calls": ["Navbar"], "search-terms": ["App", "React", "theme", "Navbar"], "state": 2, "file_id": 3, "knowledge_revision": 51, "git_revision": "a4ba1140e6770be6da5f71b292e5bd80c1c443a5", "revision_history": [{"24": "678d0233a9198408c19e44be1859ba3c532a7587"}, {"30": "678d0233a9198408c19e44be1859ba3c532a7587"}, {"51": "a4ba1140e6770be6da5f71b292e5bd80c1c443a5"}], "ctags": [{"_type": "tag", "name": "App", "path": "/tmp/kavia/workspace/code-generation/simple-notes-web-app-201-210/react_frontend/src/App.js", "pattern": "/^function App() {$/", "language": "JavaScript", "kind": "function", "signature": "()"}], "hash": "566dcaae884848436ce1451d0a8eb3a5", "format-version": 4, "code-base-name": "react_frontend", "filename": "react_frontend/src/App.js"}