{"is_source_file": true, "format": "JavaScript", "description": "A React context implementation for managing theme state (light/dark) within a web application.", "external_files": [], "external_methods": [], "published": ["ThemeContext", "ThemeProvider", "useTheme"], "classes": [], "methods": [{"name": "ThemeProvider({ children, initial = \"light\" })", "description": "Context Provider based component that manages the theme state and applies it to the document.", "scope": "", "scopeKind": ""}, {"name": "useTheme()", "description": "Custom hook to access and manipulate the theme context.", "scope": "", "scopeKind": ""}], "calls": ["useContext(ThemeContext)", "setTheme", "document.documentElement.setAttribute", "document.body.classList.toggle"], "search-terms": ["ThemeContext", "ThemeProvider", "useTheme"], "state": 2, "file_id": 20, "knowledge_revision": 49, "git_revision": "", "ctags": [{"_type": "tag", "name": "ThemeContext", "path": "/tmp/kavia/workspace/code-generation/simple-notes-web-app-201-210/react_frontend/src/ThemeContext.js", "pattern": "/^export const ThemeContext = createContext({$/", "language": "JavaScript", "kind": "constant"}, {"_type": "tag", "name": "ThemeProvider", "path": "/tmp/kavia/workspace/code-generation/simple-notes-web-app-201-210/react_frontend/src/ThemeContext.js", "pattern": "/^export function ThemeProvider({ children, initial = \"light\" }) {$/", "language": "JavaScript", "kind": "function", "signature": "({ children, initial = \"light\" })"}, {"_type": "tag", "name": "theme", "path": "/tmp/kavia/workspace/code-generation/simple-notes-web-app-201-210/react_frontend/src/ThemeContext.js", "pattern": "/^    theme,$/", "language": "JavaScript", "kind": "field", "scope": "ThemeProvider.value", "scopeKind": "class"}, {"_type": "tag", "name": "useTheme", "path": "/tmp/kavia/workspace/code-generation/simple-notes-web-app-201-210/react_frontend/src/ThemeContext.js", "pattern": "/^export function useTheme() {$/", "language": "JavaScript", "kind": "function", "signature": "()"}, {"_type": "tag", "name": "value", "path": "/tmp/kavia/workspace/code-generation/simple-notes-web-app-201-210/react_frontend/src/ThemeContext.js", "pattern": "/^  return <ThemeContext.Provider value={value}>{children}<\\/ThemeContext.Provider>;$/", "language": "JavaScript", "kind": "field", "scope": "Provider", "scopeKind": "class"}], "hash": "50f069d220a82881f871b072d5a6a31e", "format-version": 4, "code-base-name": "react_frontend", "filename": "react_frontend/src/ThemeContext.js", "fields": [{"name": "theme,", "scope": "ThemeProvider.value", "scopeKind": "class", "description": "unavailable"}, {"name": "return <ThemeContext.Provider value={value}>{children}<\\/ThemeContext.Provider>;", "scope": "Provider", "scopeKind": "class", "description": "unavailable"}], "revision_history": [{"49": ""}]}